<Turns>
  <Turn id="1" speaker="spk1" startTime="0.646" endTime="1.958" words="word_1..word_3" />
  <Turn id="2" speaker="spk2" startTime="1.958" endTime="9.835" words="word_4..word_19" />
  <Turn id="3" speaker="spk2" startTime="9.835" endTime="10.363" words="empty" />
  <Turn id="4" speaker="spk1" startTime="9.835" endTime="10.363" words="word_20" />
  <Turn id="5" speaker="spk1" startTime="10.363" endTime="11.465" words="word_21..word_24" />
  <Turn id="6" speaker="spk2" startTime="11.465" endTime="13.531" words="word_25..word_28" />
  <Turn id="7" speaker="spk1" startTime="13.531" endTime="14.503" words="word_29..word_31" />
  <Turn id="8" speaker="spk2" startTime="14.503" endTime="17.135" words="word_32..word_37" />
  <Turn id="9" speaker="spk1" startTime="17.135" endTime="24.419" words="word_38..word_52" />
  <Turn id="10" speaker="spk2" startTime="24.419" endTime="27.37" words="word_53..word_61" />
  <Turn id="11" speaker="spk1" startTime="27.37" endTime="28.889" words="word_62..word_64" />
  <Turn id="12" speaker="spk2" startTime="28.889" endTime="31.627" words="word_65..word_72" />
  <Turn id="13" speaker="spk1" startTime="31.627" endTime="32.285" words="word_73..word_74" />
</Turns>