<Chunks>
  <chunk id="1" span="word_1" cat="PN" />
  <chunk id="2" span="word_2..word_3" cat="NP" main="word_2" />
  <chunk id="3" span="word_4..word_5" cat="NP" main="word_4" />
  <chunk id="4" span="word_6" cat="NP" main="word_6" />
  <chunk id="5" span="word_7" cat="VP" main="word_7" />
  <chunk id="6" span="word_8" cat="NP_PRON" />
  <chunk id="7" span="word_9" cat="VP_INF" />
  <chunk id="8" span="word_10" cat="NP_PRON" />
  <chunk id="9" span="word_11" cat="PP" />
  <chunk id="10" span="word_12" cat="PN" />
  <chunk id="11" span="word_13" cat="CC" />
  <chunk id="12" span="word_14" cat="CC" />
  <chunk id="13" span="word_15" cat="PART" />
  <chunk id="14" span="word_16" cat="VP" main="word_16" />
  <chunk id="15" span="word_17..word_18" cat="NP" main="word_18" />
  <chunk id="16" span="word_19" cat="PREL" />
  <chunk id="17" span="word_20" cat="VP" main="word_20" />
  <chunk id="18" span="word_21" cat="CC" />
  <chunk id="19" span="word_22" cat="NP" main="word_22" />
  <chunk id="20" span="word_23..word_24" cat="PN" />
  <chunk id="21" span="word_25" cat="CC" />
  <chunk id="22" span="word_26" cat="NP_PRON" />
  <chunk id="23" span="word_27" cat="VP" main="word_27" />
  <chunk id="24" span="word_28" cat="VP_INF" />
  <chunk id="25" span="word_29" cat="PP" />
  <chunk id="26" span="word_30..word_31" cat="PN" />
  <chunk id="27" span="word_32" cat="PART" />
  <chunk id="28" span="word_33" cat="PP" />
  <chunk id="29" span="word_34" cat="PN" />
  <chunk id="30" span="word_35" cat="PART" />
  <chunk id="31" span="word_36" cat="PP" />
  <chunk id="32" span="word_37..word_38" cat="PN" />
  <chunk id="33" span="word_39" cat="VP" main="word_39" />
  <chunk id="34" span="word_40" cat="NP" main="word_40" />
  <chunk id="35" span="word_41" cat="NP" main="word_41" />
  <chunk id="36" span="word_42..word_43" cat="NUM" />
  <chunk id="37" span="word_44" cat="CC" />
  <chunk id="38" span="word_45..word_46" cat="NUM" />
  <chunk id="39" span="word_47" cat="ITJ" />
  <chunk id="40" span="word_48" cat="CC" />
  <chunk id="41" span="word_49" cat="NP_PRON" />
  <chunk id="42" span="word_50" cat="VP" main="word_50" />
  <chunk id="43" span="word_51" cat="PP" />
  <chunk id="44" span="word_52" cat="PN" />
  <chunk id="45" span="word_53" cat="ADJP" />
  <chunk id="46" span="word_54" cat="PART" />
  <chunk id="47" span="word_55" cat="PP" />
  <chunk id="48" span="word_56..word_57" cat="PN" />
  <chunk id="49" span="word_58" cat="NUM" />
  <chunk id="50" span="word_59" cat="NUM" />
  <chunk id="51" span="word_60" cat="NUM" />
  <chunk id="52" span="word_61" cat="NUM" />
  <chunk id="53" span="word_62" cat="NUM" />
  <chunk id="54" span="word_63..word_64" cat="NUM" />
  <chunk id="55" span="word_65" cat="NUM" />
  <chunk id="56" span="word_66" cat="NUM" />
  <chunk id="57" span="word_67" cat="NP" main="word_67" />
  <chunk id="58" span="word_68" cat="NP_PRON" />
  <chunk id="59" span="word_69" cat="NP_PRON" />
  <chunk id="60" span="word_70" cat="PREF" />
  <chunk id="61" span="word_71" cat="VP" main="word_71" />
  <chunk id="62" span="word_72" cat="NUM" />
  <chunk id="63" span="word_73" cat="NUM" />
  <chunk id="64" span="word_74" cat="CC" />
  <chunk id="65" span="word_75..word_76" cat="NUM" />
  <chunk id="66" span="word_77" cat="CC" />
  <chunk id="67" span="word_78..word_79" cat="NUM" />
  <chunk id="68" span="word_80..word_81" cat="NUM" />
  <chunk id="69" span="word_82" cat="PART" />
  <chunk id="70" span="word_83" cat="PP" />
  <chunk id="71" span="word_84..word_85" cat="PN" />
  <chunk id="72" span="word_86" cat="VP" main="word_86" />
  <chunk id="73" span="word_87" cat="NP" main="word_87" />
  <chunk id="74" span="word_89" cat="PART" />
  <chunk id="75" span="word_90" cat="NP" main="word_90" />
  <chunk id="76" span="word_92" cat="PP" />
  <chunk id="77" span="word_93..word_94" cat="PN" />
  <chunk id="78" span="word_95" cat="PP" />
  <chunk id="79" span="word_96..word_97" cat="PN" />
  <chunk id="80" span="word_98..word_99" cat="NUM" />
  <chunk id="81" span="word_100" cat="CC" />
  <chunk id="82" span="word_101" cat="PP" />
  <chunk id="83" span="word_102..word_103" cat="PN" />
  <chunk id="84" span="word_104" cat="CC" />
  <chunk id="85" span="word_105" cat="VP" main="word_105" />
  <chunk id="86" span="word_106" cat="PART" />
  <chunk id="87" span="word_107" cat="PP" />
  <chunk id="88" span="word_108" cat="PP" />
  <chunk id="89" span="word_109" cat="PN" />
  <chunk id="90" span="word_111" cat="PART" />
  <chunk id="91" span="word_112" cat="PART" />
  <chunk id="92" span="word_114" cat="PP" />
  <chunk id="93" span="word_115" cat="PN" />
  <chunk id="94" span="word_116" cat="VP" main="word_116" />
  <chunk id="95" span="word_117" cat="PART" />
  <chunk id="96" span="word_118" cat="ITJ" />
  <chunk id="97" span="word_119..word_120" cat="NUM" />
  <chunk id="98" span="word_121" cat="VP" main="word_121" />
  <chunk id="99" span="word_122" cat="PP" />
  <chunk id="100" span="word_123" cat="NP" main="word_123" />
  <chunk id="101" span="word_124" cat="VP" main="word_124" />
  <chunk id="102" span="word_125" cat="PP" />
  <chunk id="103" span="word_126" cat="NP" main="word_126" />
</Chunks>