<Turns>
<Turn id="1" speaker="spk1" startTime="0.539" endTime="16.905" words="word_1..word_24"/>
<Turn id="2" speaker="spk2" startTime="16.905" endTime="20.83" words="word_25"/>
<Turn id="3" speaker="spk1" startTime="20.83" endTime="27.565" words="word_26..word_42"/>
<Turn id="4" speaker="spk2" startTime="27.565" endTime="28.270" words="word_43..word_45"/>
<Turn id="5" speaker="spk1" startTime="28.270" endTime="36.727" words="word_46..word_61"/>
<Turn id="6" speaker="spk2" startTime="36.727" endTime="39.083" words="word_62..word_63"/>
<Turn id="7" speaker="spk1" startTime="39.083" endTime="46.863" words="word_64..word_75"/>
<Turn id="8" speaker="spk2" startTime="46.863" endTime="49.291" words="word_76"/>
<Turn id="9" speaker="spk1" startTime="49.291" endTime="56.456" words="word_77..word_92"/>
<Turn id="10" speaker="spk2" startTime="56.456" endTime="57.326" words="word_93"/>
<Turn id="11" speaker="spk1" startTime="57.326" endTime="78.338" words="word_94..word_140"/>
<Turn id="12" speaker="spk2" startTime="78.338" endTime="79.314" words="word_141"/>
<Turn id="13" speaker="spk1" startTime="79.314" endTime="82.603" words="word_142..word_146"/>
<Turn id="14" speaker="spk2" startTime="82.603" endTime="84.183" words="word_147"/>
<Turn id="15" speaker="spk1" startTime="84.183" endTime="87.437" words="word_148..word_152"/>
</Turns>
